{"version":1,"resource":"file:///home/pancake/Documents/TeamProject28/frontend/src/pages/dashboard_pages/Todo-list.tsx","entries":[{"id":"o1vu.tsx","timestamp":1760634219292},{"id":"1g0n.tsx","timestamp":1760634455565},{"id":"Kiml.tsx","timestamp":1760634567218},{"id":"v8pX.tsx","timestamp":1760634605517},{"id":"9EeE.tsx","timestamp":1760634627869},{"id":"F9PK.tsx","timestamp":1760634648669},{"id":"d8k0.tsx","timestamp":1760634699741},{"id":"HLsy.tsx","timestamp":1760634767916},{"id":"OvdC.tsx","timestamp":1760634779250},{"id":"ev72.tsx","timestamp":1760634854176},{"id":"XToF.tsx","timestamp":1760636647599},{"id":"fu6c.tsx","timestamp":1760710711158},{"id":"MIdV.tsx","timestamp":1760710920336},{"id":"4B2Z.tsx","timestamp":1760710971365},{"id":"BheA.tsx","timestamp":1760710995796},{"id":"gFtG.tsx","source":"moved.source","sourceDescription":"~/Documents/TeamProject28/frontend/src/pages/dashboard_pages/To-dolist.tsx","timestamp":1760711272379},{"id":"9mjb.tsx","source":"moved.source","sourceDescription":"~/Documents/TeamProject28/t/src/pages/dashboard_pages/To-dolist.tsx","timestamp":1760711446776},{"id":"YnIq.tsx","timestamp":1760711564234},{"id":"VjgP.tsx","timestamp":1760712716378},{"id":"3pB0.tsx","timestamp":1760715810746},{"id":"dk9t.tsx","timestamp":1760719079647},{"id":"qWW9.tsx","timestamp":1760719111471},{"id":"Pjgw.tsx","timestamp":1760719240525},{"id":"eUa6.tsx","timestamp":1760719252509},{"id":"rDps.tsx","timestamp":1760796347392},{"id":"RatA.tsx","timestamp":1760796365448},{"id":"eiph.tsx","timestamp":1760796512013},{"id":"AEA8.tsx","timestamp":1760892114067},{"id":"H9jR.tsx","timestamp":1760892156182},{"id":"JCBX.tsx","timestamp":1760892800153},{"id":"O7fS.tsx","source":"renamed.source","sourceDescription":"~/Documents/TeamProject28/frontend/src/pages/dashboard_pages/To-dolist.tsx","timestamp":1760948668112},{"id":"f0UA.tsx","source":"Workspace Edit","timestamp":1760948746213},{"id":"uBRa.tsx","timestamp":1761304804979},{"id":"0uEG.tsx","timestamp":1761305860968},{"id":"2ekG.tsx","source":"undoRedo.source","timestamp":1761857601604},{"id":"jqR8.tsx","source":"Workspace Edit","timestamp":1762107409611}]}